pysas/__init__.py
pysas/pysas.py
pyxmmsas/__init__.py
pyxmmsas/extract_spectra.py
pyxmmsas-1.4.24.dist-info/LICENSE
pyxmmsas-1.4.24.dist-info/METADATA
pyxmmsas-1.4.24.dist-info/WHEEL
pyxmmsas-1.4.24.dist-info/top_level.txt
pyxmmsas-1.4.24.dist-info/RECORD
