Metadata-Version: 2.1
Name: pyxmmsas
Version: 1.4.24
Summary: It is wrapper for SAS and performs spectral analysis and plots
Home-page: https://gitlab.astro.unige.ch/ferrigno/pysas
Author: Carlo Ferrigno
Author-email: carlo.ferrigno@unige.ch
License: MIT
Requires-Python: >=3.0
License-File: LICENSE
Requires-Dist: astropy !=3.0.*,!=3.1,!=3.1.1,>=2.0.12
Requires-Dist: numpy
Requires-Dist: astroquery
Requires-Dist: matplotlib
Requires-Dist: scipy
Requires-Dist: photutils
Requires-Dist: optimalgrouping >=1.0.3
Requires-Dist: adaptivelcbin
Requires-Dist: cython
Requires-Dist: ultranest
Requires-Dist: bxa >=4.0.5
Requires-Dist: ipython
